rivalz_client/__init__.py
rivalz_client/client.py
tests/__init__.py
tests/test_client.py
rivalz_py_client-0.1.8.dist-info/LICENSE
rivalz_py_client-0.1.8.dist-info/METADATA
rivalz_py_client-0.1.8.dist-info/WHEEL
rivalz_py_client-0.1.8.dist-info/top_level.txt
rivalz_py_client-0.1.8.dist-info/RECORD
