Metadata-Version: 2.1
Name: rivalz-py-client
Version: 0.1.8
Summary: A Python client for interacting with Rivalz API
Home-page: https://github.com/Rivalz-ai/pyhon-client/
Author: Bui Dinh Ngoc
Author-email: buidinhngoc.aiti@gmail.com
License: UNKNOWN
Platform: UNKNOWN
Classifier: Programming Language :: Python :: 3
Classifier: License :: OSI Approved :: MIT License
Classifier: Operating System :: OS Independent
Requires-Python: >=3.6
License-File: LICENSE
Requires-Dist: python-dotenv (>=1.0.0)
Requires-Dist: requests (>=2.28.2)
